VisualLog/LogParser.py
VisualLog/MatplotlibZoom.py
VisualLog/SameLines.py
VisualLog/ShellCmd.py
VisualLog/__init__.py
VisualLog-0.0.16.dist-info/METADATA
VisualLog-0.0.16.dist-info/WHEEL
VisualLog-0.0.16.dist-info/top_level.txt
VisualLog-0.0.16.dist-info/RECORD
