Metadata-Version: 2.1
Name: VisualLog
Version: 0.0.16
Summary: Visual Log
Home-page: https://github.com/ZengjfOS/VisualLog
Author: zengjf
Author-email: zengjf42@163.com
Project-URL: Bug Tracker, https://github.com/ZengjfOS/VisualLog/issues
Classifier: Programming Language :: Python :: 3
Classifier: License :: OSI Approved :: MIT License
Classifier: Operating System :: OS Independent
Requires-Python: >=3.0
Requires-Dist: matplotlib
Requires-Dist: numpy
